CongDevopsDaoAiopsYunweiJishuJingxuan/README.md
CongDevopsDaoAiopsYunweiJishuJingxuan/__init__.py
CongDevopsDaoAiopsYunweiJishuJingxuan/__main__.py
CongDevopsDaoAiopsYunweiJishuJingxuan/file.pdf
CongDevopsDaoAiopsYunweiJishuJingxuan/index.html
cong_devops_dao_aiops_yunwei_jishu_jingxuan-2024.3.5.0.dist-info/METADATA
cong_devops_dao_aiops_yunwei_jishu_jingxuan-2024.3.5.0.dist-info/WHEEL
cong_devops_dao_aiops_yunwei_jishu_jingxuan-2024.3.5.0.dist-info/entry_points.txt
cong_devops_dao_aiops_yunwei_jishu_jingxuan-2024.3.5.0.dist-info/top_level.txt
cong_devops_dao_aiops_yunwei_jishu_jingxuan-2024.3.5.0.dist-info/RECORD
